<?xml version="1.0" encoding="UTF-8"?>
<glosario>
	<letra id="a">
	<definicao>
			<titulo>ALIMENTAÇÃO</titulo>
			<conteudo>
				Processo biológico e cultural que se traduz na escolha, preparação e consumo de um ou vários alimentos.
			</conteudo>
		</definicao>
	</letra>
	<letra id="b">
		<definicao>
			<titulo>BULIMIA</titulo>
			<conteudo>
				Distúrbio  alimentar  multideterminado  por  fatores  biológicos,  psicológicos, familiares  e  culturais  de  fundo  psicológico,caracterizado pelo impulso irresistível de comer seguido por sentimento de culpa e de vergonha, o que faz com que a pessoa provoque vômito e use laxativos e/ou diuréticos de maneira exagerada.
			</conteudo>
		</definicao>
	</letra>
	<letra id="c">
		<definicao>
			<titulo>CARÊNCIA NUTRICIONAL</titulo>
			<conteudo>
				Situação em que deficiências gerais ou específicas de energia e nutrientes
                resultam na instalação de processos orgânicos adversos para a saúde.
			</conteudo>
		</definicao>
	</letra>
	<letra id="d">
		<definicao>
			<titulo>DESIDRATAÇÃO</titulo>
			<conteudo>
				A desidratação resulta da eliminação de água e sais minerais do organismo e acontece quando o balanço hídrico é negativo, quando as perdas de água não são repostas.
			</conteudo>
		</definicao>
		<definicao>
			<titulo>DIGESTÃO</titulo>
			<conteudo>
				Transformação dos alimentos ingeridos em substâncias mais simples, ao longo do tubo digestivo, através de processos mecânicos e químicos.
			</conteudo>
		</definicao>
		<definicao>
			<titulo>DISPEPSIA</titulo>
			<conteudo>
				Digestão difícil e dolorosa; qualquer que seja a causa.
			</conteudo>
		</definicao>
		<definicao>
			<titulo>DISTÚRBIO ALIMENTAR COMPULSIVO</titulo>
			<conteudo>
				Quem sofre de distúrbio alimentar compulsivo passa o dia a comer, come excessivamente às escondidas ou sente-se incapaz de controlar a comida que ingere.
			</conteudo>
		</definicao>
		<definicao>
			<titulo>DIVERTÍCULO</titulo>
			<conteudo>
				Cavidade em forma de saco, anatómica ou patológica, que é projectada através da parede intestinal para fora do intestino.
			</conteudo>
		</definicao>
		<definicao>
			<titulo>DOSE DIÁRIA RECOMENDADA (DDR)</titulo>
			<conteudo>
				Estabelecido pela União Europeia, representa a quantidade mínima diária de vitaminas e minerais, recomendada para satisfazer as necessidades de um indivíduo adulto.
			</conteudo>
		</definicao>
		<definicao>
			<titulo>DESIDRATAÇÃO</titulo>
			<conteudo>
				A desidratação resulta da eliminação de água e sais minerais do organismo e acontece quando o balanço hídrico é negativo, quando as perdas de água não são repostas.
			</conteudo>
		</definicao>
		<definicao>
			<titulo>DIGESTÃO</titulo>
			<conteudo>
				Transformação dos alimentos ingeridos em substâncias mais simples, ao longo do tubo digestivo, através de processos mecânicos e químicos.
			</conteudo>
		</definicao>
		<definicao>
			<titulo>DISPEPSIA</titulo>
			<conteudo>
				Digestão difícil e dolorosa; qualquer que seja a causa.
			</conteudo>
		</definicao>
		<definicao>
			<titulo>DISTÚRBIO ALIMENTAR COMPULSIVO</titulo>
			<conteudo>
				Quem sofre de distúrbio alimentar compulsivo passa o dia a comer, come excessivamente às escondidas ou sente-se incapaz de controlar a comida que ingere.
			</conteudo>
		</definicao>
		<definicao>
			<titulo>DIVERTÍCULO</titulo>
			<conteudo>
				Cavidade em forma de saco, anatómica ou patológica, que é projectada através da parede intestinal para fora do intestino.
			</conteudo>
		</definicao>
		<definicao>
			<titulo>DOSE DIÁRIA RECOMENDADA (DDR)</titulo>
			<conteudo>
				Estabelecido pela União Europeia, representa a quantidade mínima diária de vitaminas e minerais, recomendada para satisfazer as necessidades de um indivíduo adulto.
			</conteudo>
		</definicao>
		<definicao>
			<titulo>DESIDRATAÇÃO</titulo>
			<conteudo>
				A desidratação resulta da eliminação de água e sais minerais do organismo e acontece quando o balanço hídrico é negativo, quando as perdas de água não são repostas.
			</conteudo>
		</definicao>
		<definicao>
			<titulo>DIGESTÃO</titulo>
			<conteudo>
				Transformação dos alimentos ingeridos em substâncias mais simples, ao longo do tubo digestivo, através de processos mecânicos e químicos.
			</conteudo>
		</definicao>
		<definicao>
			<titulo>DISPEPSIA</titulo>
			<conteudo>
				Digestão difícil e dolorosa; qualquer que seja a causa.
			</conteudo>
		</definicao>
		<definicao>
			<titulo>DISTÚRBIO ALIMENTAR COMPULSIVO</titulo>
			<conteudo>
				Quem sofre de distúrbio alimentar compulsivo passa o dia a comer, come excessivamente às escondidas ou sente-se incapaz de controlar a comida que ingere.
			</conteudo>
		</definicao>
		<definicao>
			<titulo>DIVERTÍCULO</titulo>
			<conteudo>
				Cavidade em forma de saco, anatómica ou patológica, que é projectada através da parede intestinal para fora do intestino.
			</conteudo>
		</definicao>
		<definicao>
			<titulo>DOSE DIÁRIA RECOMENDADA (DDR)</titulo>
			<conteudo>
				Estabelecido pela União Europeia, representa a quantidade mínima diária de vitaminas e minerais, recomendada para satisfazer as necessidades de um indivíduo adulto.
			</conteudo>
		</definicao>
		<definicao>
			<titulo>DESIDRATAÇÃO</titulo>
			<conteudo>
				A desidratação resulta da eliminação de água e sais minerais do organismo e acontece quando o balanço hídrico é negativo, quando as perdas de água não são repostas.
			</conteudo>
		</definicao>
		<definicao>
			<titulo>DIGESTÃO</titulo>
			<conteudo>
				Transformação dos alimentos ingeridos em substâncias mais simples, ao longo do tubo digestivo, através de processos mecânicos e químicos.
			</conteudo>
		</definicao>
		<definicao>
			<titulo>DISPEPSIA</titulo>
			<conteudo>
				Digestão difícil e dolorosa; qualquer que seja a causa.
			</conteudo>
		</definicao>
		<definicao>
			<titulo>DISTÚRBIO ALIMENTAR COMPULSIVO</titulo>
			<conteudo>
				Quem sofre de distúrbio alimentar compulsivo passa o dia a comer, come excessivamente às escondidas ou sente-se incapaz de controlar a comida que ingere.
			</conteudo>
		</definicao>
		<definicao>
			<titulo>DIVERTÍCULO</titulo>
			<conteudo>
				Cavidade em forma de saco, anatómica ou patológica, que é projectada através da parede intestinal para fora do intestino.
			</conteudo>
		</definicao>
		<definicao>
			<titulo>DOSE DIÁRIA RECOMENDADA (DDR)</titulo>
			<conteudo>
				Estabelecido pela União Europeia, representa a quantidade mínima diária de vitaminas e minerais, recomendada para satisfazer as necessidades de um indivíduo adulto.
			</conteudo>
		</definicao>
	</letra>
	<letra id="e">
		<definicao>
			<titulo>ESTADO NUTRICIONAL</titulo>
			<conteudo>
				Resultado do equilíbrio entre o consumo de nutrientes e o gasto energético do organismo para suprir as necessidades nutricionais, em plano individual ou coletivo.
			</conteudo>
		</definicao>
	</letra>
	<letra id="f">
		<definicao>
			<titulo>FRACIONAMENTO DE ALIMENTOS</titulo>
			<conteudo>
				Operações  por  meio  das  quais se divide um alimento sem modificar a sua composição original.
			</conteudo>
		</definicao>
	</letra>
	<letra id="g">
		<definicao>
			<titulo>GRUPO DE ALIMENTOS</titulo>
			<conteudo>
				Conjunto de alimentos in natura ou processados que são agrupados de acordo com os principais nutrientes que os compõem.
			</conteudo>
		</definicao>
	</letra>
	<letra id="h">
		<definicao>
			<titulo>HÁBITOS SAUDÁVEIS</titulo>
			<conteudo>
				Conjunto de atos e atitudes que visam àmanutenção da saúde e qualidade de vida.
			</conteudo>
		</definicao>
	</letra>
	<letra id="i">
		<definicao>
			<titulo>HÁBITOS SAUDÁVEIS</titulo>
			<conteudo>
				É o que proporciona informações relevantes sobre determinados atributos e
				dimensões do estado de saúde, bem como sobre o desempenho do sistema de saúde.
			</conteudo>
		</definicao>
	</letra>
	<letra id="j">
	</letra>
	<letra id="k">
	</letra>
	<letra id="l">
		<definicao>
			<titulo>LACTOSE</titulo>
			<conteudo>
				Tipo de hidrato de carbono presente no leite, composto por uma molécula de glicose e uma de galactose. Vulgarmente conhecido como “açúcar” do leite.
			</conteudo>
		</definicao>
	</letra>
	<letra id="m">
		<definicao>
			<titulo>MANIPULAÇÃO DE ALIMENTOS</titulo>
			<conteudo>
				Conjunto de procedimentos e técnicas operacionais aplicadas aos alimentos, desde o tratamento da matéria-prima até a obtenção do alimento acabado.
			</conteudo>
		</definicao>
	</letra>
	<letra id="n">
		<definicao>
			<titulo>NUTRIÇÃO</titulo>
			<conteudo>
				Estado fisiológico que resulta do consumo e da utilização biológica de energia e nutrientes em nível celular.
			</conteudo>
		</definicao>
	</letra>
	<letra id="o">
		<definicao>
			<titulo>OBESIDADE</titulo>
			<conteudo>
				Doença crônica de natureza multifatorial (fatores ambientais, nutricionais e genéticos) caracterizada pelo acúmulo excessivo de gordura no corpo, acarretando prejuízos à saúde.
			</conteudo>
		</definicao>
	</letra>
	<letra id="p">
		<definicao>
			<titulo>PIRÂMIDE ALIMENTAR</titulo>
			<conteudo>
				Guia alimentar que representa graficamente, na forma de pirâmide,
				seis grupos básicos de alimentos.
			</conteudo>
		</definicao>
	</letra>
	<letra id="q">
		<definicao>
			<titulo>QUITOSANO</titulo>
			<conteudo>
				Polissacarídeo natural extraído da casca de alguns crustáceos (lagosta, caranguejo ou camarão) que, tal como a fibra dietética, não é digerido nem absorvido pelo organismo humano, formando um volumoso gel no tracto gastro-intestinal capaz de captar nutrientes e outras toxinas.
			</conteudo>
		</definicao>
	</letra>
	<letra id="r">
		<definicao>
			<titulo>ROTULAGEM NUTRICIONAL</titulo>
			<conteudo>
				Informação ao consumidor sobre os componentes nutricionais de um alimento ou de sua preparação, incluindo a declaração de valor energético e de nutrientes que o compõem.
			</conteudo>
		</definicao>
	</letra>
	<letra id="s">
		<definicao>
			<titulo>SOBREPESO</titulo>
			<conteudo>
				Excesso de peso de um indivíduo quando em comparação com tabelas ou padrões de normalidade.
			</conteudo>
		</definicao>
	</letra>
	<letra id="t">
		<definicao>
			<titulo>TRANSTORNO ALIMENTAR</titulo>
			<conteudo>
				Distúrbio que se refere à nutrição e ao comportamento anormal de indivíduos em relação à ingestão de alimentos.
			</conteudo>
		</definicao>
	</letra>
	<letra id="u">
	</letra>
	<letra id="v">
		<definicao>
			<titulo>VIGILÂNCIA NUTRICIONAL</titulo>
			<conteudo>
				Informações  sobre  o  estado  de  nutrição dos grupos biológicos (crianças, gestantes) e sociais (baixa renda) mais expostos aos problemas da nutrição.
			</conteudo>
		</definicao>
	</letra>
	<letra id="w">
	</letra>
	<letra id="x">
		<definicao>
			<titulo>XEROFTALMIA</titulo>
			<conteudo>
				Alterações oculares decorrentes da deficiência grave de vitamina A.
			</conteudo>
		</definicao>
	</letra>
	<letra id="y">
	</letra>
	<letra id="z">
	</letra>
</glosario>